MANIFEST.in
README.rst
setup.py
docker_console/__init__.py
docker_console/__main__.py
docker_console/version.py
docker_console.egg-info/PKG-INFO
docker_console.egg-info/SOURCES.txt
docker_console.egg-info/dependency_links.txt
docker_console.egg-info/entry_points.txt
docker_console.egg-info/not-zip-safe
docker_console.egg-info/requires.txt
docker_console.egg-info/top_level.txt
docker_console/bash_completion/__init__.py
docker_console/bash_completion/__init__.pyc
docker_console/bash_completion/template.sh
docker_console/bash_completion/__pycache__/__init__.cpython-38.pyc
docker_console/db/__init__.py
docker_console/db/drivers/__init__.py
docker_console/db/drivers/base.py
docker_console/db/drivers/mysql.py
docker_console/docker_init_templates/drupal7/.gitignore
docker_console/docker_init_templates/drupal7/README.md
docker_console/docker_init_templates/drupal7/docker-compose-template.yml
docker_console/docker_init_templates/drupal7/docker-compose.yml-tpl
docker_console/docker_init_templates/drupal7/app_conf/settings.php
docker_console/docker_init_templates/drupal7/app_conf/settings_include/settings.dev.inc
docker_console/docker_init_templates/drupal7/app_data/README.txt
docker_console/docker_init_templates/drupal7/app_databases/README.txt
docker_console/docker_init_templates/drupal7/app_files/README.txt
docker_console/docker_init_templates/drupal7/docker/custom_config/README.txt
docker_console/docker_init_templates/drupal7/docker/custom_config/my.cnf
docker_console/docker_init_templates/drupal7/docker/custom_images/README.txt
docker_console/docker_init_templates/drupal7/docker_console/dc_overrides.py
docker_console/docker_init_templates/drupal7/docker_console/dc_settings.py-tpl
docker_console/docker_init_templates/drupal8/.gitignore
docker_console/docker_init_templates/drupal8/README.md
docker_console/docker_init_templates/drupal8/docker-compose-template.yml
docker_console/docker_init_templates/drupal8/docker-compose.yml-tpl
docker_console/docker_init_templates/drupal8/app_conf/settings.local.php
docker_console/docker_init_templates/drupal8/app_conf/settings.php
docker_console/docker_init_templates/drupal8/app_data/README.txt
docker_console/docker_init_templates/drupal8/app_databases/README.txt
