Metadata-Version: 2.1
Name: docker-console
Version: 1.0.24
Summary: Application that improves and speeds up web development process using Docker
Home-page: https://github.com/droptica/docker-console
Download-URL: https://github.com/droptica/docker-console/archive/v1.0.24.tar.gz
Author: Droptica
Author-email: admin@droptica.com
License: MIT
